recurvedata/__init__.py
recurvedata/agent/__init__.py
recurvedata/agent/_version.py
recurvedata/agent/config.py
recurvedata/agent/exceptions.py
recurvedata/agent/utils.py
recurvedata/agent/_commands/__init__.py
recurvedata/agent/_commands/_typer.py
recurvedata/agent/_commands/agent.py
recurvedata/agent/_commands/config.py
recurvedata/agent/_commands/main.py
recurvedata/agent/_commands/service.py
recurvedata/agent/_internal/__init__.py
recurvedata/agent/_internal/agent.py
recurvedata/agent/_internal/client.py
recurvedata/agent/_internal/host.py
recurvedata/agent/_internal/schemas.py
recurvedata/agent/_internal/service_loop.py
recurvedata/agent/_internal/task_executor.py
recurvedata/agent/_internal/task_scheduler.py
recurvedata/agent/_internal/utils.py
recurvedata/agent/_internal/worker.py
recurve_agent-0.7.5.dist-info/METADATA
recurve_agent-0.7.5.dist-info/WHEEL
recurve_agent-0.7.5.dist-info/entry_points.txt
recurve_agent-0.7.5.dist-info/RECORD
